lfcdemolib/ArgparsePromptDefault.py
lfcdemolib/ConnectionSecretManager.py
lfcdemolib/DatabaseSetupValidator.py
lfcdemolib/DbxRest.py
lfcdemolib/DemoInstance.py
lfcdemolib/ImpactAssessment.py
lfcdemolib/LfcCDC.py
lfcdemolib/LfcCDCBase.py
lfcdemolib/LfcCDCPostgreSQL.py
lfcdemolib/LfcCDCSqlServer.py
lfcdemolib/LfcConn.py
lfcdemolib/LfcCredentialModel.py
lfcdemolib/LfcDbPerm.py
lfcdemolib/LfcEnv.py
lfcdemolib/LfcNotebookConfig.py
lfcdemolib/LfcSchEvo.py
lfcdemolib/LfcScheduler.py
lfcdemolib/LfcSecrets.py
lfcdemolib/LfcToken.py
lfcdemolib/PerformanceReporter.py
lfcdemolib/SimpleAlter.py
lfcdemolib/SimpleAzure.py
lfcdemolib/SimpleCloudBase.py
lfcdemolib/SimpleConn.py
lfcdemolib/SimpleDB.py
lfcdemolib/SimpleDDL.py
lfcdemolib/SimpleDML.py
lfcdemolib/SimpleLocalCred.py
lfcdemolib/SimpleMonitor.py
lfcdemolib/SimpleMonitorBase.py
lfcdemolib/SimpleMonitorMySQL.py
lfcdemolib/SimpleMonitorNew.py
lfcdemolib/SimpleMonitorPostgreSQL.py
lfcdemolib/SimpleMonitorSqlServer.py
lfcdemolib/SimpleReport.py
lfcdemolib/SimpleSqlalchemy.py
lfcdemolib/SimpleTest.py
lfcdemolib/TestAsyncParallel.py
lfcdemolib/TestComprehensive.py
lfcdemolib/TestDedicatedSchema.py
lfcdemolib/TestDmlOnly.py
lfcdemolib/TestFullDatabase.py
lfcdemolib/TestScenarioRunner.py
lfcdemolib/__init__.py
lfcdemolib/__version__.py
lfcdemolib/_pydantic_compat.py
lfcdemolib-0.0.7.dist-info/licenses/LICENSE
lfcdemolib-0.0.7.dist-info/METADATA
lfcdemolib-0.0.7.dist-info/WHEEL
lfcdemolib-0.0.7.dist-info/entry_points.txt
lfcdemolib-0.0.7.dist-info/top_level.txt
lfcdemolib-0.0.7.dist-info/RECORD
