Metadata-Version: 2.4
Name: lfcdemolib
Version: 0.0.7
Summary: Lakeflow Connect Demo Library
Home-page: https://github.com/databricks-labs/lfcdemolib
Author: Databricks Labs
Author-email: Databricks Labs <labs@databricks.com>
Maintainer-email: Databricks Labs <labs@databricks.com>
License: Databricks Labs License
Project-URL: Homepage, https://github.com/databricks-labs/lfcdemolib
Project-URL: Documentation, https://github.com/databricks-labs/lfcdemolib#readme
Project-URL: Repository, https://github.com/databricks-labs/lfcdemolib
Project-URL: Bug Tracker, https://github.com/databricks-labs/lfcdemolib/issues
Keywords: databricks,lakeflow,federation,cdc,change-data-capture,data-engineering,etl,database,replication
Classifier: Development Status :: 4 - Beta
Classifier: Intended Audience :: Developers
Classifier: Intended Audience :: Information Technology
Classifier: License :: Other/Proprietary License
Classifier: Operating System :: OS Independent
Classifier: Programming Language :: Python :: 3
Classifier: Programming Language :: Python :: 3.8
Classifier: Programming Language :: Python :: 3.9
Classifier: Programming Language :: Python :: 3.10
Classifier: Programming Language :: Python :: 3.11
Classifier: Programming Language :: Python :: 3.12
Classifier: Topic :: Database
Classifier: Topic :: Software Development :: Libraries :: Python Modules
Classifier: Topic :: System :: Monitoring
Requires-Python: >=3.8
License-File: LICENSE
Requires-Dist: sqlalchemy<3.0.0,>=1.4.0
Requires-Dist: pandas>=1.3.0
Requires-Dist: databricks-sdk>=0.1.0
Requires-Dist: apscheduler<4.0.0,>=3.9.0
Requires-Dist: pydantic>=1.10.0
Requires-Dist: requests>=2.25.0
Requires-Dist: pymysql>=1.0.0
Requires-Dist: psycopg2-binary>=2.9.0
Requires-Dist: pymssql>=2.2.0
Requires-Dist: oracledb>=1.0.0
Provides-Extra: dev
Requires-Dist: pytest>=6.0; extra == "dev"
Requires-Dist: pytest-cov>=3.0; extra == "dev"
Requires-Dist: black>=21.0; extra == "dev"
Requires-Dist: flake8>=3.8; extra == "dev"
Requires-Dist: mypy>=0.900; extra == "dev"
Requires-Dist: isort>=5.10; extra == "dev"
Provides-Extra: docs
Requires-Dist: sphinx>=4.0; extra == "docs"
Requires-Dist: sphinx-rtd-theme>=1.0; extra == "docs"
Requires-Dist: myst-parser>=0.18; extra == "docs"
Dynamic: author
Dynamic: home-page
Dynamic: license-file
Dynamic: requires-python
